abetter/__init__.py
abetter/ab.py
abetter/sample_basic.py
abetter/sample_mean.py
abetter/sample_prop.py
abetter/srm.py
abetter/io/__init__.py
abetter/io/data.py
abetter/io/format.py
abetter/io/plot.py
abetter/io/to_html.py
abetter/test/__init__.py
abetter/test/all_test_function.py
abetter/test/one_sample_mean_t_test.py
abetter/test/one_sample_mean_z_test.py
abetter/test/srm_test.py
abetter/test/two_inde_mean_t_test.py
abetter/test/two_inde_mean_z_test.py
abetter/test/two_inde_prop_fisher_exact_test.py
abetter/test/two_inde_prop_z_test.py
abetter/test/two_inde_var_f_test.py
abetter/test/two_pair_mean_t_test.py
abetter-0.0.3.dist-info/METADATA
abetter-0.0.3.dist-info/WHEEL
abetter-0.0.3.dist-info/licenses/LICENSE
abetter-0.0.3.dist-info/RECORD
