Metadata-Version: 2.4
Name: ABetter
Version: 0.0.3
Summary: An A/B-testing package
Project-URL: Homepage, https://github.com/SqRoots/abetter/
Author-email: Li Xuan <lixuan.xyz@gmail.com>
License-Expression: MIT
License-File: LICENSE
Classifier: Operating System :: OS Independent
Classifier: Programming Language :: Python :: 3
Requires-Python: >=3.8
